AFQ_Browser-0.4.6.data/scripts/afqbrowser-assemble
AFQ_Browser-0.4.6.data/scripts/afqbrowser-publish
AFQ_Browser-0.4.6.data/scripts/afqbrowser-run
afqbrowser/__init__.py
afqbrowser/browser.py
afqbrowser/gh_pages.py
afqbrowser/version.py
afqbrowser/site/client/example-analysis.ipynb
afqbrowser/site/client/favicon.ico
afqbrowser/site/client/index.html
afqbrowser/site/client/index.ipynb
afqbrowser/site/client/requirements.txt
afqbrowser/site/client/settings.json
afqbrowser/site/client/css/dat-gui-afq.css
afqbrowser/site/client/css/style.css
afqbrowser/site/client/data/afq.mat
afqbrowser/site/client/data/freesurf.OBJ
afqbrowser/site/client/data/nodes.csv
afqbrowser/site/client/data/streamlines.json
afqbrowser/site/client/data/subjects.csv
afqbrowser/site/client/data/tracula_data/nodes.csv
afqbrowser/site/client/data/tracula_data/streamlines.json
afqbrowser/site/client/data/tracula_data/subjects.csv
afqbrowser/site/client/data/tracula_data/stats/fmajor_PP.avg33_mni_bbr.AD.txt
afqbrowser/site/client/data/tracula_data/stats/fmajor_PP.avg33_mni_bbr.AD_Avg.txt
afqbrowser/site/client/data/tracula_data/stats/fmajor_PP.avg33_mni_bbr.FA.txt
afqbrowser/site/client/data/tracula_data/stats/fmajor_PP.avg33_mni_bbr.FA_Avg.txt
afqbrowser/site/client/data/tracula_data/stats/fmajor_PP.avg33_mni_bbr.MD.txt
afqbrowser/site/client/data/tracula_data/stats/fmajor_PP.avg33_mni_bbr.MD_Avg.txt
afqbrowser/site/client/data/tracula_data/stats/fmajor_PP.avg33_mni_bbr.RD.txt
afqbrowser/site/client/data/tracula_data/stats/fmajor_PP.avg33_mni_bbr.RD_Avg.txt
afqbrowser/site/client/data/tracula_data/stats/fmajor_PP.avg33_mni_bbr.coords.mean.txt
afqbrowser/site/client/data/tracula_data/stats/fmajor_PP.avg33_mni_bbr.inputs.txt
afqbrowser/site/client/data/tracula_data/stats/fmajor_PP.avg33_mni_bbr.log
afqbrowser/site/client/data/tracula_data/stats/fmajor_PP.avg33_mni_bbr.path.mean.txt
afqbrowser/site/client/data/tracula_data/stats/fminor_PP.avg33_mni_bbr.AD.txt
AFQ_Browser-0.4.6.dist-info/LICENSE.txt
AFQ_Browser-0.4.6.dist-info/METADATA
AFQ_Browser-0.4.6.dist-info/WHEEL
AFQ_Browser-0.4.6.dist-info/top_level.txt
AFQ_Browser-0.4.6.dist-info/RECORD
